wrs/__init__.py
wrs-0.1.dist-info/LICENCE.txt
wrs-0.1.dist-info/METADATA
wrs-0.1.dist-info/WHEEL
wrs-0.1.dist-info/top_level.txt
wrs-0.1.dist-info/RECORD
