Metadata-Version: 2.1
Name: wrs
Version: 0.1
Summary: Split string without eliminating delimeter
Home-page: UNKNOWN
Author: Rao Hamza
Author-email: UNKNOWN
License: UNKNOWN
Platform: UNKNOWN
